{
  "profile": "quantum/dev",
  "events": [
    {
      "id": "obs:1",
      "kind": "observation",
      "type": "quantum.job.submitted",
      "ts": "2026-02-24T16:40:46.106884Z",
      "data": {
        "modality": "event",
        "value": {
          "note": "example observation"
        },
        "note": "starter"
      }
    },
    {
      "id": "der:1",
      "kind": "derivation",
      "type": "quantum.circuit.compiled",
      "ts": "2026-02-24T16:40:46.106884Z",
      "refs": [
        "obs:1"
      ],
      "method": "system",
      "data": {
        "name": "example_feature",
        "value": 0.42,
        "unit": "1"
      }
    },
    {
      "id": "clm:1",
      "kind": "claim",
      "type": "quantum.mapping.selected",
      "ts": "2026-02-24T16:40:46.106884Z",
      "refs": [
        "der:1"
      ],
      "method": "heuristic",
      "confidence": 0.66,
      "alternates": [
        {
          "id": "alt:1",
          "statement": "alternate interpretation",
          "refs": [
            "der:1"
          ],
          "confidence": 0.22,
          "method": "heuristic"
        }
      ],
      "data": {
        "statement": "primary interpretation"
      }
    },
    {
      "id": "cue:1",
      "kind": "cue",
      "type": "quantum.run.executed",
      "ts": "2026-02-24T16:40:46.106884Z",
      "refs": [
        "clm:1"
      ],
      "data": {
        "channel": "text",
        "intent": "inform",
        "urgency": "normal",
        "payload": {
          "text": "Example cue grounded in claim clm:1"
        }
      }
    }
  ],
  "extensions": {
    "quantum": {
      "_x": {
        "stub": true
      }
    }
  }
}
